padar_parallel/__init__.py
padar_parallel/for_loop.py
padar_parallel/groupby.py
padar_parallel/grouper.py
padar_parallel/join.py
padar_parallel/sort.py
padar_parallel/windowing.py
padar_parallel/tests/__init__.py
padar_parallel/tests/test_for_loop.py
padar_parallel/tests/test_groupby.py
padar_parallel/tests/test_grouper.py
padar_parallel-0.2.11.dist-info/METADATA
padar_parallel-0.2.11.dist-info/RECORD
padar_parallel-0.2.11.dist-info/WHEEL
padar_parallel-0.2.11.dist-info/top_level.txt
