Metadata-Version: 2.1
Name: padar-parallel
Version: 0.2.11
Summary: Extension to do parallel computing on grouped chunks or files
Home-page: UNKNOWN
Author: UNKNOWN
Author-email: UNKNOWN
License: UNKNOWN
Platform: UNKNOWN
Requires-Dist: dask[complete] (>=1.1.1)
Requires-Dist: padar-converter (>=0.2.13)
